lambdadb/__init__.py
lambdadb/_hooks/__init__.py
lambdadb/_hooks/registration.py
lambdadb/_hooks/sdkhooks.py
lambdadb/_hooks/types.py
lambdadb/_version.py
lambdadb/basesdk.py
lambdadb/collections.py
lambdadb/docs.py
lambdadb/errors/__init__.py
lambdadb/errors/apierror.py
lambdadb/errors/badrequest_error.py
lambdadb/errors/internalservererror.py
lambdadb/errors/lambdadberror.py
lambdadb/errors/no_response_error.py
lambdadb/errors/resourcealreadyexists_error.py
lambdadb/errors/resourcenotfound_error.py
lambdadb/errors/responsevalidationerror.py
lambdadb/errors/toomanyrequests_error.py
lambdadb/errors/unauthenticated_error.py
lambdadb/httpclient.py
lambdadb/models/__init__.py
lambdadb/models/bulkupsertdocsop.py
lambdadb/models/collectionresponse.py
lambdadb/models/createcollectionop.py
lambdadb/models/deletecollectionop.py
lambdadb/models/deletedocsop.py
lambdadb/models/fetchdocsop.py
lambdadb/models/getbulkupsertdocsop.py
lambdadb/models/getcollectionop.py
lambdadb/models/indexconfigs_union.py
lambdadb/models/listcollectionsop.py
lambdadb/models/messageresponse.py
lambdadb/models/querycollectionop.py
lambdadb/models/security.py
lambdadb/models/status.py
lambdadb/models/updatecollectionop.py
lambdadb/models/updatedocsop.py
lambdadb/models/upsertdocsop.py
lambdadb/py.typed
lambdadb/sdk.py
lambdadb/sdkconfiguration.py
lambdadb/types/__init__.py
lambdadb/types/basemodel.py
lambdadb/utils/__init__.py
lambdadb/utils/annotations.py
lambdadb/utils/datetimes.py
lambdadb/utils/enums.py
lambdadb/utils/eventstreaming.py
lambdadb/utils/forms.py
lambdadb/utils/headers.py
lambdadb/utils/logger.py
lambdadb/utils/metadata.py
lambdadb/utils/queryparams.py
lambdadb/utils/requestbodies.py
lambdadb/utils/retries.py
lambdadb/utils/security.py
lambdadb/utils/serializers.py
lambdadb/utils/unmarshal_json_response.py
lambdadb/utils/url.py
lambdadb/utils/values.py
lambdadb-0.5.11.dist-info/LICENSE
lambdadb-0.5.11.dist-info/METADATA
lambdadb-0.5.11.dist-info/WHEEL
lambdadb-0.5.11.dist-info/RECORD
