Metadata-Version: 2.3
Name: lambdadb
Version: 0.5.11
Summary: The Official LambdaDB Python SDK.
Author: Functional Systems, Inc.
Requires-Python: >=3.9.2
Classifier: Programming Language :: Python :: 3
Classifier: Programming Language :: Python :: 3.10
Classifier: Programming Language :: Python :: 3.11
Classifier: Programming Language :: Python :: 3.12
Classifier: Programming Language :: Python :: 3.13
Requires-Dist: httpcore (>=1.0.9)
Requires-Dist: httpx (>=0.28.1)
Requires-Dist: pydantic (>=2.11.2)
Project-URL: Documentation, https://docs.lambdadb.ai
Project-URL: Homepage, https://lambdadb.ai
Project-URL: Repository, https://github.com/lambdadb/lambdadb-python-client.git
